pyomt/__init__.py
pyomt/__version__.py
pyomt/maxsat/__init__.py
pyomt/maxsat/bs.py
pyomt/maxsat/fm.py
pyomt/maxsat/lsu.py
pyomt/maxsat/maxsat_solver.py
pyomt/maxsat/rc2.py
pyomt/maxsat/rc2_z3.py
pyomt/omtarith/__init__.py
pyomt/omtarith/arith_opt_lp.py
pyomt/omtarith/arith_opt_qsmt.py
pyomt/omtarith/arith_opt_search.py
pyomt/omtarith/boxed/__init__.py
pyomt/omtarith/boxed/arith_boxed_seq.py
pyomt/omtarith/boxed/arith_boxed_symba.py
pyomt/omtbv/__init__.py
pyomt/omtbv/bit_blast_omt_solver.py
pyomt/omtbv/bv_blast.py
pyomt/omtbv/bv_opt_iterative_search.py
pyomt/omtbv/bv_opt_maxsat.py
pyomt/omtbv/bv_opt_qsmt.py
pyomt/omtbv/bv_opt_utils.py
pyomt/omtbv/boxed/__init__.py
pyomt/omtbv/boxed/bv_boxed_compact.py
pyomt/omtbv/boxed/bv_boxed_obj_divide.py
pyomt/omtbv/boxed/bv_boxed_seq.py
pyomt/solver_process/__init__.py
pyomt/solver_process/server.py
pyomt/solver_process/solver.py
pyomt/solver_process/solver_utils.py
pyomt/utils/__init__.py
pyomt/utils/bin_solver.py
pyomt/utils/config.py
pyomt/utils/mapped_blast.py
pyomt/utils/new_config.py
pyomt/utils/opt_parser.py
pyomt/utils/portfolio.py
pyomt/utils/portfolio_ipc.py
pyomt/utils/pysmt_utils.py
pyomt/utils/smt_exceptions.py
pyomt/utils/smt_model_parse.py
pyomt/utils/smt_results_parser.py
pyomt/utils/z3expr_utils.py
pyomt/utils/z3opt_utils.py
pyomt-0.0.3.dist-info/LICENSE
pyomt-0.0.3.dist-info/METADATA
pyomt-0.0.3.dist-info/WHEEL
pyomt-0.0.3.dist-info/top_level.txt
pyomt-0.0.3.dist-info/RECORD
